typed_json_db/__init__.py
typed_json_db/database.py
typed_json_db/exceptions.py
typed_json_db/py.typed
typed_json_db-0.3.0.dist-info/METADATA
typed_json_db-0.3.0.dist-info/WHEEL
typed_json_db-0.3.0.dist-info/entry_points.txt
typed_json_db-0.3.0.dist-info/licenses/LICENSE
typed_json_db-0.3.0.dist-info/RECORD
