Metadata-Version: 2.4
Name: typed-json-db
Version: 0.3.0
Summary: A simple JSON-based database for Python applications
Project-URL: Homepage, https://github.com/frangiz/typed-json-db
Project-URL: Repository, https://github.com/frangiz/typed-json-db
Project-URL: Issues, https://github.com/frangiz/typed-json-db/issues
Project-URL: Documentation, https://github.com/frangiz/typed-json-db#readme
Author-email: frangiz <frangiz@gmail.com>
Maintainer-email: frangiz <frangiz@gmail.com>
License: MIT License
License-File: LICENSE
Keywords: database,dataclass,json,persistence,storage,typed
Classifier: Development Status :: 4 - Beta
Classifier: Intended Audience :: Developers
Classifier: License :: OSI Approved :: MIT License
Classifier: Operating System :: OS Independent
Classifier: Programming Language :: Python :: 3
Classifier: Programming Language :: Python :: 3.11
Classifier: Programming Language :: Python :: 3.12
Classifier: Programming Language :: Python :: 3.13
Classifier: Topic :: Database
Classifier: Topic :: Software Development :: Libraries :: Python Modules
Requires-Python: >=3.11
